{
  "test_metrics": {
    "mae": 0.2465423066900669,
    "rmse": 0.32155391994686017,
    "r2": 0.0,
    "r2_prod": 0.0,
    "mase": 0.0
  },
  "cv_aggregate": {
    "mae_mean": 0.1630666541511442,
    "mae_std": 0.09407174329042164,
    "mase_mean": 2.2450337878674445,
    "mase_std": 3.1749572307879816,
    "r2_mean": -7.066233398205521,
    "r2_std": 9.99316310663597,
    "r2_prod_mean": -2.357816464990383,
    "r2_prod_std": 3.3344560223759876,
    "rmse_mean": 0.20747366868870443,
    "rmse_std": 0.1156792920621657
  },
  "cv_fold_results": [
    {
      "fold_idx": 0,
      "metrics": {
        "mae": 0.18946998432812936,
        "rmse": 0.24143093445257457,
        "r2": -21.198700194616563,
        "r2_prod": -7.073449394971149,
        "mase": 6.735101363602333
      },
      "history": {
        "epochs_run": 100,
        "best_epoch": 94,
        "stopped_early": false,
        "final_train_loss": 0.07329342456068844,
        "final_val_loss": 0.0001298078673244163
      },
      "cost": {
        "wall_time_seconds": 390.58,
        "gpu_memory_peak_mb": 387.89,
        "param_count": 2250842,
        "trainable_params": 2250842,
        "model_size_mb": 8.5863
      }
    },
    {
      "fold_idx": 1,
      "metrics": {
        "mae": 0.26278703051259317,
        "rmse": 0.3290869763891393,
        "r2": 0.0,
        "r2_prod": 0.0,
        "mase": 0.0
      },
      "history": {
        "epochs_run": 83,
        "best_epoch": 62,
        "stopped_early": true,
        "final_train_loss": 0.05420444769755242,
        "final_val_loss": 0.002671756054951402
      },
      "cost": {
        "wall_time_seconds": 417.01,
        "gpu_memory_peak_mb": 387.18,
        "param_count": 2250842,
        "trainable_params": 2250842,
        "model_size_mb": 8.5863
      }
    },
    {
      "fold_idx": 2,
      "metrics": {
        "mae": 0.0369429476127101,
        "rmse": 0.05190309522439936,
        "r2": 0.0,
        "r2_prod": 0.0,
        "mase": 0.0
      },
      "history": {
        "epochs_run": 100,
        "best_epoch": 92,
        "stopped_early": false,
        "final_train_loss": 0.04068748992455157,
        "final_val_loss": 6.7582200244942214e-06
      },
      "cost": {
        "wall_time_seconds": 621.7,
        "gpu_memory_peak_mb": 387.89,
        "param_count": 2250842,
        "trainable_params": 2250842,
        "model_size_mb": 8.5863
      }
    }
  ],
  "retrain_history": {
    "epochs_run": 25,
    "best_epoch": 4,
    "stopped_early": true,
    "final_train_loss": 0.10189304334275863,
    "final_val_loss": 0.000596056372160092
  },
  "n_train": 6024,
  "n_test": 1506,
  "n_retrain_train": 5422,
  "n_retrain_val": 602,
  "n_cv_folds": 3,
  "experiment_name": "unknown"
}